[
    {
        "Display Name": "Ari Anne",
        "Discord User ID": "332976738646622208",
        "Date & Time": "2023-12-28 11:01 AM UTC"
    },
    {
        "Display Name": "Gamxel",
        "Discord User ID": "222980392393637888",
        "Date & Time": "2024-01-05 11:02 AM UTC"
    },
    {
        "Display Name": "Unknown (195744338142167040)",
        "Discord User ID": "195744338142167040",
        "Date & Time": "2024-02-27 11:02 AM UTC"
    },
    {
        "Display Name": "Holy Hades69",
        "Discord User ID": "987970552834719754",
        "Date & Time": "2024-05-07 10:14 AM UTC"
    },
    {
        "Display Name": "iRiot | iHeero",
        "Discord User ID": "151906298957529089",
        "Date & Time": "2024-01-27 11:02 AM UTC"
    },
    {
        "Display Name": "Jess (Trapvis Scott)",
        "Discord User ID": "222546371465445376",
        "Date & Time": "2024-01-19 11:03 AM UTC"
    },
    {
        "Display Name": "PainfulSmack",
        "Discord User ID": "285112809434644480",
        "Date & Time": "2024-04-20 11:03 AM UTC"
    },
    {
        "Display Name": "pearlaries",
        "Discord User ID": "161182153584017408",
        "Date & Time": "2024-02-07 11:03 AM UTC"
    },
    {
        "Display Name": "cs.briar",
        "Discord User ID": "403948983690461184",
        "Date & Time": "2024-08-28 09:01 PM UTC"
    },
    {
        "Display Name": "CommonOne",
        "Discord User ID": "163019344907862016",
        "Date & Time": "2024-10-03 09:57 AM UTC"
    },
    {
        "Display Name": "Ghosted Nova | Nova Chroma (RS3)",
        "Discord User ID": "111970622573219840",
        "Date & Time": "2024-10-03 01:16 AM UTC"
    },
    {
        "Display Name": "GhostedGrim",
        "Discord User ID": "283121397532852225",
        "Date & Time": "2024-11-11 05:57 PM UTC"
    },
    {
        "Display Name": "Stackless",
        "Discord User ID": "147980497576919040",
        "Date & Time": "2024-12-07 12:32 AM UTC"
    },
    {
        "Display Name": "retlr3855",
        "Discord User ID": "201389399861100544",
        "Date & Time": "2025-02-07 04:57 AM UTC"
    },
    {
        "Display Name": "Trhea | Sylist",
        "Discord User ID": "171657409339588608",
        "Date & Time": 1739219875
    }
]